responsinator/__init__.py
responsinator/exceptions.py
responsinator-1.0.1.dist-info/LICENSE.txt
responsinator-1.0.1.dist-info/METADATA
responsinator-1.0.1.dist-info/WHEEL
responsinator-1.0.1.dist-info/top_level.txt
responsinator-1.0.1.dist-info/RECORD
