Metadata-Version: 2.1
Name: responsinator
Version: 1.0.1
Summary: HTTP Response SDK
Home-page: https://github.com/hdsme/responsinator
Download-URL: https://github.com/hdsme/responsinator/tarball/1.0.1
Author: Hao Hoang
Author-email: haohoangofficial@gmail.com
License: LICENSE.txt
License-File: LICENSE.txt
Requires-Dist: python-executor-sd
